simplt/__init__.py
simplt/__main__.py
simplt/export_plot.py
simplt/helper.py
simplt/arg_parser/__init__.py
simplt/arg_parser/arg_parser.py
simplt/arg_parser/process_args.py
simplt/box_plot/__init__.py
simplt/box_plot/box_plot.py
simplt/latex_table/__init__.py
simplt/latex_table/latex_table.py
simplt/line_plot/__init__.py
simplt/line_plot/line_plot.py
simplt-0.0.5.dist-info/METADATA
simplt-0.0.5.dist-info/WHEEL
simplt-0.0.5.dist-info/entry_points.txt
simplt-0.0.5.dist-info/licence
simplt-0.0.5.dist-info/top_level.txt
simplt-0.0.5.dist-info/RECORD
