Metadata-Version: 2.1
Name: simplt
Version: 0.0.5
Summary: Makes plotting matplotlib easy.
Home-page: https://github.com/a-t-0/simplt
Author: a-t-0
Author-email: no-email@no-email.org
Maintainer: a-t-0
Maintainer-email: no-email@no-email.org
License: AGPLv3
Classifier: Development Status :: 2 - Pre-Alpha
Classifier: Environment :: Console
Classifier: Intended Audience :: Science/Research
Classifier: License :: OSI Approved :: GNU Affero General Public License v3
Classifier: Programming Language :: Python
Classifier: Programming Language :: Python :: 3
Classifier: Programming Language :: Python :: 3 :: Only
Classifier: Programming Language :: Python :: 3.10
Classifier: Topic :: Scientific/Engineering :: Visualization
Requires-Python: >=3.10
License-File: licence
Requires-Dist: matplotlib >=3.6.1
Requires-Dist: numpy >=1.23.4
Requires-Dist: pyannotate >=1.2.0
Requires-Dist: pytest-cov >=4.0.0
Requires-Dist: typeguard >=2.13.3
